[
  {
    "description": "Checks that all list items are in alphabetical order",
    "patternId": "remark-lint-alphabetize-lists",
    "timeToFix": 5,
    "title": "Checks that all list items are in alphabetical order"
  },
  {
    "description": "Check that the top-level heading matches the directory name",
    "patternId": "remark-lint-appropriate-heading",
    "timeToFix": 5,
    "title": "Check that the top-level heading matches the directory name"
  },
  {
    "description": "This package allows to check either a link points to the existing resource. ",
    "patternId": "remark-lint-are-links-valid",
    "timeToFix": 5,
    "title": "This package allows to check either a link points to the existing resource. "
  },
  {
    "description": "Checks that all titles are followed by 1 blank line, then no blank lines, then two blank lines before the next title",
    "patternId": "remark-lint-blank-lines-1-0-2",
    "timeToFix": 5,
    "title": "Checks that all titles are followed by 1 blank line, then no blank lines, then two blank lines before the next title"
  },
  {
    "parameters": [
      {
        "description": "remark-lint-blockquote-indentation",
        "name": "remark-lint-blockquote-indentation"
      }
    ],
    "description": "Warn when block quotes are indented too much or too little.",
    "patternId": "remark-lint-blockquote-indentation",
    "timeToFix": 5,
    "title": "Warn when block quotes are indented too much or too little."
  },
  {
    "parameters": [
      {
        "description": "remark-lint-checkbox-character-style",
        "name": "remark-lint-checkbox-character-style"
      }
    ],
    "description": "Warn when list item checkboxes violate a given style.",
    "patternId": "remark-lint-checkbox-character-style",
    "timeToFix": 5,
    "title": "Warn when list item checkboxes violate a given style."
  },
  {
    "description": "Warn when list item checkboxes are followed by too much whitespace.",
    "patternId": "remark-lint-checkbox-content-indent",
    "timeToFix": 5,
    "title": "Warn when list item checkboxes are followed by too much whitespace."
  },
  {
    "parameters": [
      {
        "description": "remark-lint-code-block-style",
        "name": "remark-lint-code-block-style"
      }
    ],
    "description": "Warn when code blocks do not adhere to a given style.",
    "patternId": "remark-lint-code-block-style",
    "timeToFix": 5,
    "title": "Warn when code blocks do not adhere to a given style."
  },
  {
    "description": "Warn when definition labels are not lowercase.",
    "patternId": "remark-lint-definition-case",
    "timeToFix": 5,
    "title": "Warn when definition labels are not lowercase."
  },
  {
    "description": "Warn when consecutive whitespace is used in a definition.",
    "patternId": "remark-lint-definition-spacing",
    "timeToFix": 5,
    "title": "Warn when consecutive whitespace is used in a definition."
  },
  {
    "description": "Only at most one emoji per paragraph.",
    "patternId": "remark-lint-emoji-limit",
    "timeToFix": 5,
    "title": "Only at most one emoji per paragraph."
  },
  {
    "parameters": [
      {
        "description": "remark-lint-emphasis-marker",
        "name": "remark-lint-emphasis-marker"
      }
    ],
    "description": "Warn for violating emphasis markers.",
    "patternId": "remark-lint-emphasis-marker",
    "timeToFix": 5,
    "title": "Warn for violating emphasis markers."
  },
  {
    "description": "Check fenced code block flags.",
    "patternId": "remark-lint-fenced-code-flag",
    "timeToFix": 5,
    "title": "Check fenced code block flags."
  },
  {
    "description": "remark-lint rule to warn when fenced code blocks have an inconsistently-cased language flag",
    "patternId": "remark-lint-fenced-code-flag-case",
    "timeToFix": 5,
    "title": "remark-lint rule to warn when fenced code blocks have an inconsistently-cased language flag"
  },
  {
    "parameters": [
      {
        "description": "remark-lint-fenced-code-marker",
        "name": "remark-lint-fenced-code-marker"
      }
    ],
    "description": "Warn for violating fenced code markers.",
    "patternId": "remark-lint-fenced-code-marker",
    "timeToFix": 5,
    "title": "Warn for violating fenced code markers."
  },
  {
    "parameters": [
      {
        "description": "remark-lint-file-extension",
        "name": "remark-lint-file-extension"
      }
    ],
    "description": "Warn when the file extension differ from the preferred extension.",
    "patternId": "remark-lint-file-extension",
    "timeToFix": 5,
    "title": "Warn when the file extension differ from the preferred extension."
  },
  {
    "description": "Warn when definitions are placed somewhere other than at the end of",
    "patternId": "remark-lint-final-definition",
    "timeToFix": 5,
    "title": "Warn when definitions are placed somewhere other than at the end of"
  },
  {
    "description": "Warn when a line feed at the end of a file is missing.",
    "patternId": "remark-lint-final-newline",
    "timeToFix": 5,
    "title": "Warn when a line feed at the end of a file is missing."
  },
  {
    "parameters": [
      {
        "description": "remark-lint-first-heading-level",
        "name": "remark-lint-first-heading-level"
      }
    ],
    "description": "Warn when the first heading has a level other than a specified value.",
    "patternId": "remark-lint-first-heading-level",
    "timeToFix": 5,
    "title": "Warn when the first heading has a level other than a specified value."
  },
  {
    "description": "Validate Markdown frontmatter YAML against an associated JSON schema — remark-lint rule plugin",
    "patternId": "remark-lint-frontmatter-schema",
    "timeToFix": 5,
    "title": "Validate Markdown frontmatter YAML against an associated JSON schema — remark-lint rule plugin"
  },
  {
    "description": "Warn when too many spaces are used to create a hard break.",
    "patternId": "remark-lint-hard-break-spaces",
    "timeToFix": 5,
    "title": "Warn when too many spaces are used to create a hard break."
  },
  {
    "description": "Warn when headings increment with more than 1 level at a time.",
    "patternId": "remark-lint-heading-increment",
    "timeToFix": 5,
    "title": "Warn when headings increment with more than 1 level at a time."
  },
  {
    "description": "A remark-lint rule to check the length of headings.",
    "patternId": "remark-lint-heading-length",
    "timeToFix": 5,
    "title": "A remark-lint rule to check the length of headings."
  },
  {
    "description": "Warn when a heading does not conform to a given style.",
    "patternId": "remark-lint-heading-style",
    "timeToFix": 5,
    "title": "Warn when a heading does not conform to a given style."
  },
  {
    "description": "Prevents non-breaking spaces from breaking headings",
    "patternId": "remark-lint-heading-whitespace",
    "timeToFix": 5,
    "title": "Prevents non-breaking spaces from breaking headings"
  },
  {
    "description": "remark-lint rule to warn when headings have too many or too few words",
    "patternId": "remark-lint-heading-word-length",
    "timeToFix": 5,
    "title": "remark-lint rule to warn when headings have too many or too few words"
  },
  {
    "description": "Warn when linebreaks violate a given or detected style.",
    "patternId": "remark-lint-linebreak-style",
    "timeToFix": 5,
    "title": "Warn when linebreaks violate a given or detected style."
  },
  {
    "parameters": [
      {
        "description": "remark-lint-link-title-style",
        "name": "remark-lint-link-title-style"
      }
    ],
    "description": "Warn when link and definition titles occur with incorrect quotes.",
    "patternId": "remark-lint-link-title-style",
    "timeToFix": 5,
    "title": "Warn when link and definition titles occur with incorrect quotes."
  },
  {
    "description": "Warn when list item bullets are indented.",
    "patternId": "remark-lint-list-item-bullet-indent",
    "timeToFix": 5,
    "title": "Warn when list item bullets are indented."
  },
  {
    "description": "Warn when the content of a list item has mixed indentation.",
    "patternId": "remark-lint-list-item-content-indent",
    "timeToFix": 5,
    "title": "Warn when the content of a list item has mixed indentation."
  },
  {
    "parameters": [
      {
        "description": "remark-lint-list-item-indent",
        "name": "remark-lint-list-item-indent"
      }
    ],
    "description": "Warn when the spacing between a list item’s bullet and its content violates",
    "patternId": "remark-lint-list-item-indent",
    "timeToFix": 5,
    "title": "Warn when the spacing between a list item’s bullet and its content violates"
  },
  {
    "description": "Warn when list looseness is incorrect, such as being tight when it should",
    "patternId": "remark-lint-list-item-spacing",
    "timeToFix": 5,
    "title": "Warn when list looseness is incorrect, such as being tight when it should"
  },
  {
    "description": "remark-lint rule to warn when list items violate a given style",
    "patternId": "remark-lint-list-item-style",
    "timeToFix": 5,
    "title": "remark-lint rule to warn when list items violate a given style"
  },
  {
    "description": "remark lint plugin that checks punctuation are used in pair",
    "patternId": "remark-lint-match-punctuation",
    "timeToFix": 5,
    "title": "remark lint plugin that checks punctuation are used in pair"
  },
  {
    "parameters": [
      {
        "description": "remark-lint-maximum-heading-length",
        "name": "remark-lint-maximum-heading-length"
      }
    ],
    "description": "Warn when headings are too long.",
    "patternId": "remark-lint-maximum-heading-length",
    "timeToFix": 5,
    "title": "Warn when headings are too long."
  },
  {
    "parameters": [
      {
        "description": "remark-lint-maximum-line-length",
        "name": "remark-lint-maximum-line-length"
      }
    ],
    "description": "Warn when lines are too long.",
    "patternId": "remark-lint-maximum-line-length",
    "timeToFix": 5,
    "title": "Warn when lines are too long."
  },
  {
    "parameters": [
      {
        "description": "remark-lint-mdash-style",
        "name": "remark-lint-mdash-style"
      }
    ],
    "description": "Warn when the mdash style violate a given style.",
    "patternId": "remark-lint-mdash-style",
    "timeToFix": 5,
    "title": "Warn when the mdash style violate a given style."
  },
  {
    "description": "Warn for autolinks without protocol.",
    "patternId": "remark-lint-no-auto-link-without-protocol",
    "timeToFix": 5,
    "title": "Warn for autolinks without protocol."
  },
  {
    "description": "Warn when blank lines without `>` (greater than) markers are found in a",
    "patternId": "remark-lint-no-blockquote-without-marker",
    "timeToFix": 5,
    "title": "Warn when blank lines without `>` (greater than) markers are found in a"
  },
  {
    "description": "remark lint plugin that warn when Chinese punctuation found in numbers.",
    "patternId": "remark-lint-no-chinese-punctuation-in-number",
    "timeToFix": 5,
    "title": "remark lint plugin that warn when Chinese punctuation found in numbers."
  },
  {
    "description": "Warn for too many consecutive blank lines.",
    "patternId": "remark-lint-no-consecutive-blank-lines",
    "timeToFix": 5,
    "title": "Warn for too many consecutive blank lines."
  },
  {
    "description": "Ensure that URLs in your Markdown are alive",
    "patternId": "remark-lint-no-dead-urls",
    "timeToFix": 5,
    "title": "Ensure that URLs in your Markdown are alive"
  },
  {
    "description": "Warn when definitions define the same URL.",
    "patternId": "remark-lint-no-duplicate-defined-urls",
    "timeToFix": 5,
    "title": "Warn when definitions define the same URL."
  },
  {
    "description": "Warn when duplicate definitions are found.",
    "patternId": "remark-lint-no-duplicate-definitions",
    "timeToFix": 5,
    "title": "Warn when duplicate definitions are found."
  },
  {
    "description": "Warn when duplicate headings are found.",
    "patternId": "remark-lint-no-duplicate-headings",
    "timeToFix": 5,
    "title": "Warn when duplicate headings are found."
  },
  {
    "description": "Warn when duplicate headings are found, but only when on the same level,",
    "patternId": "remark-lint-no-duplicate-headings-in-section",
    "timeToFix": 5,
    "title": "Warn when duplicate headings are found, but only when on the same level,"
  },
  {
    "description": "Warn when emphasis (including strong), instead of a heading, introduces",
    "patternId": "remark-lint-no-emphasis-as-heading",
    "timeToFix": 5,
    "title": "Warn when emphasis (including strong), instead of a heading, introduces"
  },
  {
    "description": "Checks that all markdown titles have a content",
    "patternId": "remark-lint-no-empty-sections",
    "timeToFix": 5,
    "title": "Checks that all markdown titles have a content"
  },
  {
    "description": "Warn for empty URLs in links and images.",
    "patternId": "remark-lint-no-empty-url",
    "timeToFix": 5,
    "title": "Warn for empty URLs in links and images."
  },
  {
    "description": "Warn when file names start with an article.",
    "patternId": "remark-lint-no-file-name-articles",
    "timeToFix": 5,
    "title": "Warn when file names start with an article."
  },
  {
    "description": "Warn when file names contain consecutive dashes.",
    "patternId": "remark-lint-no-file-name-consecutive-dashes",
    "timeToFix": 5,
    "title": "Warn when file names contain consecutive dashes."
  },
  {
    "parameters": [
      {
        "description": "remark-lint-no-file-name-irregular-characters",
        "name": "remark-lint-no-file-name-irregular-characters"
      }
    ],
    "description": "Warn when file names contain irregular characters: characters other than",
    "patternId": "remark-lint-no-file-name-irregular-characters",
    "timeToFix": 5,
    "title": "Warn when file names contain irregular characters: characters other than"
  },
  {
    "description": "Warn when file names use mixed case: both upper- and lowercase characters.",
    "patternId": "remark-lint-no-file-name-mixed-case",
    "timeToFix": 5,
    "title": "Warn when file names use mixed case: both upper- and lowercase characters."
  },
  {
    "description": "Warn when file names contain initial or final dashes (hyphen-minus, `-`).",
    "patternId": "remark-lint-no-file-name-outer-dashes",
    "timeToFix": 5,
    "title": "Warn when file names contain initial or final dashes (hyphen-minus, `-`)."
  },
  {
    "description": "Warn when content of headings is indented.",
    "patternId": "remark-lint-no-heading-content-indent",
    "timeToFix": 5,
    "title": "Warn when content of headings is indented."
  },
  {
    "description": "Warn when a heading is indented.",
    "patternId": "remark-lint-no-heading-indent",
    "timeToFix": 5,
    "title": "Warn when a heading is indented."
  },
  {
    "description": "Warn for h7+ “headings”.",
    "patternId": "remark-lint-no-heading-like-paragraph",
    "timeToFix": 5,
    "title": "Warn for h7+ “headings”."
  },
  {
    "parameters": [
      {
        "description": "remark-lint-no-heading-punctuation",
        "name": "remark-lint-no-heading-punctuation"
      }
    ],
    "description": "Warn when a heading ends with a group of characters.",
    "patternId": "remark-lint-no-heading-punctuation",
    "timeToFix": 5,
    "title": "Warn when a heading ends with a group of characters."
  },
  {
    "description": "Warn when HTML nodes are used.",
    "patternId": "remark-lint-no-html",
    "timeToFix": 5,
    "title": "Warn when HTML nodes are used."
  },
  {
    "description": "Warn when phrasing content is padded with spaces between their markers and",
    "patternId": "remark-lint-no-inline-padding",
    "timeToFix": 5,
    "title": "Warn when phrasing content is padded with spaces between their markers and"
  },
  {
    "description": "Warn for literal URLs in text.",
    "patternId": "remark-lint-no-literal-urls",
    "timeToFix": 5,
    "title": "Warn for literal URLs in text."
  },
  {
    "description": "Warn when missing blank lines before block content (and frontmatter",
    "patternId": "remark-lint-no-missing-blank-lines",
    "timeToFix": 5,
    "title": "Warn when missing blank lines before block content (and frontmatter"
  },
  {
    "parameters": [
      {
        "description": "remark-lint-no-multiple-toplevel-headings",
        "name": "remark-lint-no-multiple-toplevel-headings"
      }
    ],
    "description": "Warn when multiple top level headings are used.",
    "patternId": "remark-lint-no-multiple-toplevel-headings",
    "timeToFix": 5,
    "title": "Warn when multiple top level headings are used."
  },
  {
    "description": "Warn when the content in paragraphs is indented.",
    "patternId": "remark-lint-no-paragraph-content-indent",
    "timeToFix": 5,
    "title": "Warn when the content in paragraphs is indented."
  },
  {
    "description": "Warn when URLs are also defined identifiers.",
    "patternId": "remark-lint-no-reference-like-url",
    "timeToFix": 5,
    "title": "Warn when URLs are also defined identifiers."
  },
  {
    "description": "Warn when shell code is prefixed by `$` (dollar sign) characters.",
    "patternId": "remark-lint-no-shell-dollars",
    "timeToFix": 5,
    "title": "Warn when shell code is prefixed by `$` (dollar sign) characters."
  },
  {
    "description": "Warn when shortcut reference images are used.",
    "patternId": "remark-lint-no-shortcut-reference-image",
    "timeToFix": 5,
    "title": "Warn when shortcut reference images are used."
  },
  {
    "description": "Warn when shortcut reference links are used.",
    "patternId": "remark-lint-no-shortcut-reference-link",
    "timeToFix": 5,
    "title": "Warn when shortcut reference links are used."
  },
  {
    "description": "Warn when tables are indented.",
    "patternId": "remark-lint-no-table-indentation",
    "timeToFix": 5,
    "title": "Warn when tables are indented."
  },
  {
    "description": "Warn when hard tabs (`\\t`) are used instead of spaces.",
    "patternId": "remark-lint-no-tabs",
    "timeToFix": 5,
    "title": "Warn when hard tabs (`\\t`) are used instead of spaces."
  },
  {
    "description": "Warn when references to undefined definitions are found.",
    "patternId": "remark-lint-no-undefined-references",
    "timeToFix": 5,
    "title": "Warn when references to undefined definitions are found."
  },
  {
    "description": "Warn when full reference images are used that could be collapsed.",
    "patternId": "remark-lint-no-unneeded-full-reference-image",
    "timeToFix": 5,
    "title": "Warn when full reference images are used that could be collapsed."
  },
  {
    "description": "Warn when full reference links are used that could be collapsed.",
    "patternId": "remark-lint-no-unneeded-full-reference-link",
    "timeToFix": 5,
    "title": "Warn when full reference links are used that could be collapsed."
  },
  {
    "description": "Warn when unused definitions are found.",
    "patternId": "remark-lint-no-unused-definitions",
    "timeToFix": 5,
    "title": "Warn when unused definitions are found."
  },
  {
    "parameters": [
      {
        "description": "remark-lint-ordered-list-marker-style",
        "name": "remark-lint-ordered-list-marker-style"
      }
    ],
    "description": "Warn when the list item marker style of ordered lists violate a given style.",
    "patternId": "remark-lint-ordered-list-marker-style",
    "timeToFix": 5,
    "title": "Warn when the list item marker style of ordered lists violate a given style."
  },
  {
    "parameters": [
      {
        "description": "remark-lint-ordered-list-marker-value",
        "name": "remark-lint-ordered-list-marker-value"
      }
    ],
    "description": "Warn when the list item marker values of ordered lists violate a given",
    "patternId": "remark-lint-ordered-list-marker-value",
    "timeToFix": 5,
    "title": "Warn when the list item marker values of ordered lists violate a given"
  },
  {
    "description": "Warn when the thematic breaks (horizontal rules) violate a given or",
    "patternId": "remark-lint-rule-style",
    "timeToFix": 5,
    "title": "Warn when the thematic breaks (horizontal rules) violate a given or"
  },
  {
    "description": "remark lint plugin that checks if there are spaces between number and Chinese",
    "patternId": "remark-lint-spaces-around-number",
    "timeToFix": 5,
    "title": "remark lint plugin that checks if there are spaces between number and Chinese"
  },
  {
    "description": "remark lint plugin that checks if there are spaces between English word and Chinese",
    "patternId": "remark-lint-spaces-around-word",
    "timeToFix": 5,
    "title": "remark lint plugin that checks if there are spaces between English word and Chinese"
  },
  {
    "parameters": [
      {
        "description": "remark-lint-strong-marker",
        "name": "remark-lint-strong-marker"
      }
    ],
    "description": "Warn for violating importance (strong) markers.",
    "patternId": "remark-lint-strong-marker",
    "timeToFix": 5,
    "title": "Warn for violating importance (strong) markers."
  },
  {
    "parameters": [
      {
        "description": "remark-lint-table-cell-padding",
        "name": "remark-lint-table-cell-padding"
      }
    ],
    "description": "Warn when table cells are incorrectly padded.",
    "patternId": "remark-lint-table-cell-padding",
    "timeToFix": 5,
    "title": "Warn when table cells are incorrectly padded."
  },
  {
    "description": "Warn when table pipes are not aligned.",
    "patternId": "remark-lint-table-pipe-alignment",
    "timeToFix": 5,
    "title": "Warn when table pipes are not aligned."
  },
  {
    "description": "Warn when table rows are not fenced with pipes.",
    "patternId": "remark-lint-table-pipes",
    "timeToFix": 5,
    "title": "Warn when table rows are not fenced with pipes."
  },
  {
    "parameters": [
      {
        "description": "remark-lint-unordered-list-marker-style",
        "name": "remark-lint-unordered-list-marker-style"
      }
    ],
    "description": "Warn when the list item marker style of unordered lists violate a given",
    "patternId": "remark-lint-unordered-list-marker-style",
    "timeToFix": 5,
    "title": "Warn when the list item marker style of unordered lists violate a given"
  },
  {
    "description": "A remark-lint rule to check each paragraph using write-good.",
    "patternId": "remark-lint-write-good",
    "timeToFix": 5,
    "title": "A remark-lint rule to check each paragraph using write-good."
  }
]